zipind/__init__.py
zipind/cli.py
zipind/config.ini
zipind/zipind.py
zipind/zipind_cli.py
zipind/zipind_core.py
zipind/zipind_utils.py
zipind-1.1.3.dist-info/AUTHORS.rst
zipind-1.1.3.dist-info/LICENSE
zipind-1.1.3.dist-info/METADATA
zipind-1.1.3.dist-info/WHEEL
zipind-1.1.3.dist-info/entry_points.txt
zipind-1.1.3.dist-info/top_level.txt
zipind-1.1.3.dist-info/RECORD
