Metadata-Version: 2.1
Name: zipind
Version: 1.1.3
Summary: zipind - From a folder, make a splitted ZIP with INDependent parts
Home-page: https://github.com/apenasrr/zipind
Author: apenasrr
Author-email: apenasrr@gmail.com
License: MIT license
Keywords: zipind
Classifier: Development Status :: 2 - Pre-Alpha
Classifier: Intended Audience :: Developers
Classifier: License :: OSI Approved :: MIT License
Classifier: Natural Language :: English
Classifier: Programming Language :: Python :: 3
Classifier: Programming Language :: Python :: 3.6
Classifier: Programming Language :: Python :: 3.7
Classifier: Programming Language :: Python :: 3.8
Requires-Python: >=3.6
License-File: LICENSE
License-File: AUTHORS.rst
Requires-Dist: Click (>=7.0)
Requires-Dist: natsort
Requires-Dist: unidecode
Requires-Dist: pandas
